jigi/__init__.py
jigi/facebook/__init__.py
jigi/facebook/download.py
jigi/facebook/helpers.py
jigi/instagram/__init__.py
jigi/instagram/download.py
jigi/utils/__init__.py
jigi/utils/utils.py
jigi/vk/__init__.py
jigi/vk/download.py
jigi/vk/helpers.py
jigi-1.0.7.dist-info/METADATA
jigi-1.0.7.dist-info/WHEEL
jigi-1.0.7.dist-info/top_level.txt
jigi-1.0.7.dist-info/RECORD
